setup.cfg
setup.py
adaptpath/__init__.py
adaptpath/_test_adaptpath_pytest.py
adaptpath/adaptpath.py
adaptpath.egg-info/PKG-INFO
adaptpath.egg-info/SOURCES.txt
adaptpath.egg-info/dependency_links.txt
adaptpath.egg-info/top_level.txt
test/__init__.py
test/env_test_env.py
test/test_adaptpath.py