Metadata-Version: 1.1
Name: adaptpath
Version: 0.3.7
Summary: convinent script to adapt python's sys.path
Home-page: https://github.com/darkdarkfruit/adaptpath
Author: darkdarkfruit
Author-email: darkdarkfruit@{nospam}gmail.com
License: MIT
Keywords: adaptpath adaptedpath adapt-path adapt path
Platform: any
Classifier: Development Status :: 5 - Production/Stable
Classifier: Intended Audience :: Developers
Classifier: License :: OSI Approved :: MIT License
Classifier: Operating System :: OS Independent
Classifier: Programming Language :: Python
Classifier: Topic :: Software Development :: Libraries
Classifier: Topic :: Utilities
Classifier: Topic :: Software Development :: Libraries :: Python Modules
